[
    {
        "name": "Washington",
        "production": 6,
        "food": 3,
        "gold": 6,
        "science": 6,
        "culture": 6,
        "happiness": 7,
        "faith": 4,
        "military": 6,
        "aggressive": 2,
        "declareWar": 4,
        "commerce": 5,
        "diplomacy": 7,
        "loyal": 7,
        "expansion": 7,
        "priorities": {
            "Tradition": 6,
            "Liberty": 9,
            "Honor": 7,
            "Commerce": 6,
            "Patronage": 6,
            "Piety": 3,
            "Rationalism": 7,
            "Freedom": 10,
            "Autocracy": 3,
            "Order": 3
        }
    },
    {
        "name": "MacDonald",
        "production": 6,
        "food": 5,
        "gold": 6,
        "science": 4,
        "culture": 9,
        "happiness": 7,
        "faith": 4,
        "military": 5,
        "aggressive": 2,
        "declareWar": 4,
        "commerce": 7,
        "diplomacy": 7,
        "loyal": 7,
        "expansion": 5,
        "priorities": {
            "Tradition": 6,
            "Liberty": 9,
            "Honor": 7,
            "Commerce": 6,
            "Patronage": 9,
            "Piety": 3,
            "Rationalism": 7,
            "Freedom": 10,
            "Autocracy": 3,
            "Order": 3
        }
    },
    {
        "name": "Vercingetorix",
        "production": 6,
        "food": 3,
        "gold": 4,
        "science": 4,
        "culture": 4,
        "happiness": 6,
        "faith": 4,
        "military": 8,
        "aggressive": 6,
        "declareWar": 5,
        "commerce": 5,
        "diplomacy": 5,
        "loyal": 4,
        "expansion": 7,
        "priorities": {
            "Tradition": 8,
            "Liberty": 6,
            "Honor": 7,
            "Commerce": 6,
            "Patronage": 3,
            "Piety": 5,
            "Rationalism": 4,
            "Freedom": 3,
            "Autocracy": 8,
            "Order": 5
        }
    },
    {
        "name": "Alaric",
        "production": 6,
        "food": 3,
        "gold": 4,
        "science": 4,
        "culture": 4,
        "happiness": 6,
        "faith": 4,
        "military": 8,
        "aggressive": 6,
        "declareWar": 5,
        "commerce": 5,
        "diplomacy": 5,
        "loyal": 4,
        "expansion": 7,
        "priorities": {
            "Tradition": 6,
            "Liberty": 7,
            "Honor": 7,
            "Commerce": 5,
            "Patronage": 3,
            "Piety": 4,
            "Rationalism": 6,
            "Freedom": 3,
            "Autocracy": 7,
            "Order": 4
        }
    },
    {
        "name": "David",
        "production": 3,
        "food": 3,
        "gold": 6,
        "science": 5,
        "culture": 7,
        "happiness": 7,
        "faith": 7,
        "military": 5,
        "aggressive": 2,
        "declareWar": 4,
        "commerce": 5,
        "diplomacy": 7,
        "loyal": 7,
        "expansion": 5,
        "priorities": {
            "Tradition": 6,
            "Liberty": 9,
            "Honor": 5,
            "Commerce": 6,
            "Patronage": 6,
            "Piety": 3,
            "Rationalism": 7,
            "Freedom": 8,
            "Autocracy": 3,
            "Order": 3
        }
    },
    {
        "name": "Vittorio",
        "production": 5,
        "food": 3,
        "gold": 6,
        "science": 5,
        "culture": 7,
        "happiness": 7,
        "faith": 4,
        "military": 6,
        "aggressive": 1,
        "declareWar": 4,
        "commerce": 5,
        "diplomacy": 7,
        "loyal": 7,
        "expansion": 5,
        "priorities": {
            "Tradition": 6,
            "Liberty": 5,
            "Honor": 3,
            "Commerce": 6,
            "Patronage": 7,
            "Piety": 3,
            "Rationalism": 6,
            "Freedom": 8,
            "Autocracy": 3,
            "Order": 3
        }
    },
    {
        "name": "Benito",
        "production": 6,
        "food": 4,
        "gold": 6,
        "science": 4,
        "culture": 5,
        "happiness": 7,
        "faith": 4,
        "military": 8,
        "aggressive": 2,
        "declareWar": 4,
        "commerce": 5,
        "diplomacy": 7,
        "loyal": 7,
        "expansion": 7,
        "priorities": {
            "Tradition": 6,
            "Liberty": 6,
            "Honor": 7,
            "Commerce": 7,
            "Patronage": 6,
            "Piety": 5,
            "Rationalism": 5,
            "Freedom": 3,
            "Autocracy": 2,
            "Order": 7
        }
    }
]
